<?xml version="1.0" encoding="UTF-8"?>
<!DOCTYPE katalog SYSTEM "katalog.dtd">

<katalog>
	<buch>
<!-- req -->
		<titel lang="de">Enigma</titel>
		<id name="isbn">9876543245</id>
		<autor id="" type="writer" order="1"></autor>
		<verlag id=""></verlag>
		<preisdaten netto="" brutto="" ust=""></preisdaten>
		<lager id="" name="">123</lager>
		<gewicht einheit="g">123</gewicht>
<!-- opt -->
		<kurzinhalt>Beschreibung</kurzinhalt>
		<container format="quader">
			<abmessung name="laenge" einheit="mm">10</abmessung>
			<abmessung name="breite" einheit="mm">15</abmessung>
			<abmessung name="hoehe" einheit="mm">5</abmessung>
		</container>
		<bild>
			<grafik src="./x.jpg"/>
		</bild>
	</buch>
	<hoerbuch>
	</hoerbuch>
</katalog>